zerokey_cli/__init__.py
zerokey_cli-0.1.0.dist-info/METADATA
zerokey_cli-0.1.0.dist-info/WHEEL
zerokey_cli-0.1.0.dist-info/entry_points.txt
zerokey_cli-0.1.0.dist-info/top_level.txt
zerokey_cli-0.1.0.dist-info/RECORD
