Metadata-Version: 2.4
Name: zerokey-cli
Version: 0.1.0
Summary: Secure & unified API key management for developers
Author-email: Anikchand <anikchand461@gmail.com>
License: MIT
Project-URL: Homepage, https://github.com/anikchand461/zerokey
Project-URL: Repository, https://github.com/anikchand461/zerokey
Classifier: Development Status :: 4 - Beta
Classifier: Intended Audience :: Developers
Classifier: License :: OSI Approved :: MIT License
Classifier: Operating System :: OS Independent
Classifier: Programming Language :: Python :: 3
Classifier: Programming Language :: Python :: 3.8
Classifier: Programming Language :: Python :: 3.9
Classifier: Programming Language :: Python :: 3.10
Classifier: Programming Language :: Python :: 3.11
Classifier: Programming Language :: Python :: 3.12
Requires-Python: >=3.8
Requires-Dist: typer>=0.12.0
Requires-Dist: rich>=13.0
Requires-Dist: requests>=2.30.0
Requires-Dist: click>=8.0
